pollination_sdk/__init__.py
pollination_sdk/api_client.py
pollination_sdk/configuration.py
pollination_sdk/exceptions.py
pollination_sdk/rest.py
pollination_sdk/api/__init__.py
pollination_sdk/api/accounts_api.py
pollination_sdk/api/api_tokens_api.py
pollination_sdk/api/applications_api.py
pollination_sdk/api/artifacts_api.py
pollination_sdk/api/jobs_api.py
pollination_sdk/api/licenses_api.py
pollination_sdk/api/orgs_api.py
pollination_sdk/api/plugins_api.py
pollination_sdk/api/projects_api.py
pollination_sdk/api/recipes_api.py
pollination_sdk/api/registries_api.py
pollination_sdk/api/runs_api.py
pollination_sdk/api/subscription_plans_api.py
pollination_sdk/api/subscriptions_api.py
pollination_sdk/api/teams_api.py
pollination_sdk/api/user_api.py
pollination_sdk/api/users_api.py
pollination_sdk/models/__init__.py
pollination_sdk/models/accessor.py
pollination_sdk/models/account_public.py
pollination_sdk/models/account_type.py
pollination_sdk/models/activation.py
pollination_sdk/models/activation_list.py
pollination_sdk/models/api_token.py
pollination_sdk/models/api_token_create.py
pollination_sdk/models/api_token_list.py
pollination_sdk/models/api_token_private.py
pollination_sdk/models/application.py
pollination_sdk/models/application_access_policy.py
pollination_sdk/models/application_access_policy_list.py
pollination_sdk/models/application_create.py
pollination_sdk/models/application_deployment.py
pollination_sdk/models/application_list.py
pollination_sdk/models/application_policy_subject.py
pollination_sdk/models/application_sort_key.py
pollination_sdk/models/application_update.py
pollination_sdk/models/application_version.py
pollination_sdk/models/application_version_list.py
pollination_sdk/models/baked_recipe.py
pollination_sdk/models/billing_info.py
pollination_sdk/models/billing_option.py
pollination_sdk/models/body_cython_function_or_method_owner_plugins_post.py
pollination_sdk/models/body_post_recipe_owner_recipes_post.py
pollination_sdk-0.43.0.dist-info/METADATA
pollination_sdk-0.43.0.dist-info/WHEEL
pollination_sdk-0.43.0.dist-info/top_level.txt
pollination_sdk-0.43.0.dist-info/RECORD
