Metadata-Version: 2.1
Name: pollination-sdk
Version: 0.43.0
Summary: pollination-server
Home-page: https://github.com/pollination/python-sdk
Author: PollinationSolutions
Author-email: info@pollination.cloud
License: UNKNOWN
Keywords: OpenAPI,OpenAPI-Generator,pollination-server
Platform: UNKNOWN
Classifier: Programming Language :: Python :: 3.6
Classifier: Programming Language :: Python :: Implementation :: CPython
Classifier: Operating System :: OS Independent
Requires-Dist: urllib3 (>=1.15)
Requires-Dist: six (>=1.10)
Requires-Dist: certifi
Requires-Dist: python-dateutil
